boundedtest/__init__.py
boundedtest/core.py
boundedtest/critical_values.py
boundedtest/detrending.py
boundedtest/lrv.py
boundedtest/noncentrality.py
boundedtest/regulated_ou.py
boundedtest/statistics.py
boundedtest-1.0.0.dist-info/licenses/LICENSE
boundedtest-1.0.0.dist-info/METADATA
boundedtest-1.0.0.dist-info/WHEEL
boundedtest-1.0.0.dist-info/top_level.txt
boundedtest-1.0.0.dist-info/RECORD
