Metadata-Version: 2.4
Name: boundedtest
Version: 1.0.0
Summary: GLS-based unit root tests for bounded time series
Home-page: https://github.com/merwanroudane/boundedtest
Author: Merwan Roudane
Author-email: Merwan Roudane <merwanroudane920@gmail.com>
Maintainer-email: Merwan Roudane <merwanroudane920@gmail.com>
License: MIT License
Project-URL: Homepage, https://github.com/merwanroudane/boundedtest
Project-URL: Documentation, https://github.com/merwanroudane/boundedtest#readme
Project-URL: Repository, https://github.com/merwanroudane/boundedtest.git
Project-URL: Issues, https://github.com/merwanroudane/boundedtest/issues
Keywords: econometrics,unit-root,bounded-processes,time-series,GLS-detrending,cointegration,statistical-tests
Classifier: Development Status :: 4 - Beta
Classifier: Intended Audience :: Science/Research
Classifier: Topic :: Scientific/Engineering :: Mathematics
Classifier: License :: OSI Approved :: MIT License
Classifier: Programming Language :: Python :: 3
Classifier: Programming Language :: Python :: 3.8
Classifier: Programming Language :: Python :: 3.9
Classifier: Programming Language :: Python :: 3.10
Classifier: Programming Language :: Python :: 3.11
Classifier: Programming Language :: Python :: 3.12
Classifier: Operating System :: OS Independent
Requires-Python: >=3.8
License-File: LICENSE
Requires-Dist: numpy>=1.20.0
Requires-Dist: scipy>=1.7.0
Requires-Dist: pandas>=1.3.0
Requires-Dist: statsmodels>=0.13.0
Provides-Extra: dev
Requires-Dist: pytest>=6.0; extra == "dev"
Requires-Dist: pytest-cov>=2.0; extra == "dev"
Requires-Dist: black>=22.0; extra == "dev"
Requires-Dist: flake8>=4.0; extra == "dev"
Requires-Dist: mypy>=0.950; extra == "dev"
Provides-Extra: docs
Requires-Dist: sphinx>=4.0; extra == "docs"
Requires-Dist: sphinx-rtd-theme>=1.0; extra == "docs"
Dynamic: author
Dynamic: home-page
Dynamic: license-file
Dynamic: requires-python
